fundosbr/__init__.py
fundosbr/__version__.py
fundosbr/fundosbr.py
fundosbr/fundosbrlib.py
fundosbr-0.1.1.dist-info/LICENSE
fundosbr-0.1.1.dist-info/METADATA
fundosbr-0.1.1.dist-info/WHEEL
fundosbr-0.1.1.dist-info/entry_points.txt
fundosbr-0.1.1.dist-info/top_level.txt
fundosbr-0.1.1.dist-info/RECORD
