Metadata-Version: 2.1
Name: fundosbr
Version: 0.1.1
Summary: Script para mostrar dados de fundos de investimento.
Home-page: https://github.com/thobiast/fundosbr
Author: Thobias Salazar Trevisan
License: MIT
Platform: UNKNOWN
Classifier: License :: OSI Approved :: MIT License
Classifier: Environment :: Console
Classifier: Topic :: Software Development
Classifier: Topic :: Terminals
Classifier: Topic :: Utilities
Classifier: Programming Language :: Python :: 3
Classifier: Intended Audience :: Developers
Classifier: Intended Audience :: System Administrators
Classifier: Operating System :: OS Independent
